{
  "code": 200,
  "data": {
    "fab_ui": {
      "fab_background_color": "4d97d0",
      "fab_image_unselected": "https://s3.amazonaws.com/entertainer-app-assets/icons/voucher_types/icFaBreservation%403x.png",
      "fab_image_selected": "https://s3.amazonaws.com/entertainer-app-assets/circle-cross.png"
    },
    "pending_orders": {
      "section_title": "DELIVERY CASHLESS",
      "section_identifier": "delivery",
      "section_list": [
        {
          "sub_title_text_color": "82d500",
          "image_url": "https://offerengine.theentertainerme.com/pizzaro-x037186/merchant_primary_logo_%28retina%29_-_merchant.jpg",
          "title_text_color": "282828",
          "sub_title": "En Route",
          "outlet_id": 3262,
          "identifier": "delivery_cashless",
          "title": "Pizzaro - Mirdif",
          "merchant_id": 2061,
          "order_id": 3777846
        },
        {
          "sub_title_text_color": "a9a9a9",
          "image_url": "https://offerengine.theentertainerme.com/les-saveurs-x23882840/merchant_primary_logo_%28retina%29_-_merchant201907231122.jpg",
          "title_text_color": "282828",
          "sub_title": "2020-04-18 12:00:00",
          "outlet_id": 76149,
          "identifier": "table_reservation",
          "title": "Les Saveurs - Wan Chai",
          "merchant_id": 43962,
          "order_id": "ET-TBL-BK-10468"
        },
        {
          "sub_title_text_color": "a9a9a9",
          "image_url": "https://offerengine.theentertainerme.com/les-saveurs-x23882840/merchant_primary_logo_%28retina%29_-_merchant201907231122.jpg",
          "title_text_color": "282828",
          "sub_title": "2020-04-18 12:00:00",
          "outlet_id": 76149,
          "identifier": "table_reservation",
          "title": "Les Saveurs - Wan Chai",
          "merchant_id": 43962,
          "order_id": "ET-TBL-BK-10467"
        }
      ],
      "section_title_color": "282828",
      "section_background_color": "f7f7f7"
    }
  },
  "cmd": "/et_rs_prd/web/v70/cashless/pending_order_status?",
  "message": "success",
  "http_response": 200,
  "success": true
}